ytget_gui/__init__.py
ytget_gui/__main__.py
ytget_gui/icon.ico
ytget_gui/main.py
ytget_gui/main_window.py
ytget_gui/settings.py
ytget_gui/styles.py
ytget_gui/dialogs/__init__.py
ytget_gui/dialogs/advanced.py
ytget_gui/dialogs/preferences.py
ytget_gui/dialogs/update_manager.py
ytget_gui/utils/__init__.py
ytget_gui/utils/firewall_manager.py
ytget_gui/utils/paths.py
ytget_gui/utils/validators.py
ytget_gui/widgets/__init__.py
ytget_gui/widgets/queue_card.py
ytget_gui/workers/__init__.py
ytget_gui/workers/cookies.py
ytget_gui/workers/cover_crop_worker.py
ytget_gui/workers/download_worker.py
ytget_gui/workers/thumb_fetcher.py
ytget_gui/workers/title_fetch_manager.py
ytget_gui/workers/title_fetcher.py
ytget_gui-2.5.2.0.dist-info/licenses/LICENSE
ytget_gui-2.5.2.0.dist-info/METADATA
ytget_gui-2.5.2.0.dist-info/WHEEL
ytget_gui-2.5.2.0.dist-info/entry_points.txt
ytget_gui-2.5.2.0.dist-info/top_level.txt
ytget_gui-2.5.2.0.dist-info/RECORD
