Metadata-Version: 2.4
Name: ytget-gui
Version: 2.5.2.0
Summary: A GUI YouTube downloader powered by yt-dlp
Author-email: Namira <erfannamira@gmail.com>
License-Expression: MIT
Project-URL: Homepage, https://github.com/ErfanNamira/ytget-gui
Project-URL: Repository, https://github.com/ErfanNamira/ytget-gui
Project-URL: Issues, https://github.com/ErfanNamira/ytget-gui/issues
Keywords: youtube-downloader,downloader,yt-dlp,yt-dlp-gui,audio-downloader,video-downloader
Classifier: Development Status :: 5 - Production/Stable
Classifier: Intended Audience :: End Users/Desktop
Classifier: Topic :: Multimedia :: Video
Classifier: Programming Language :: Python :: 3
Classifier: Programming Language :: Python :: 3.13
Requires-Python: >=3.13
License-File: LICENSE
Requires-Dist: yt-dlp
Requires-Dist: PySide6
Requires-Dist: requests
Requires-Dist: mutagen
Requires-Dist: Pillow
Requires-Dist: packaging
Dynamic: license-file
